{"games":[{"roundname":"Round 1","venue":"East Melbourne","is_grand_final":0,"winnerteamid":19,"ascore":64,"date":"1910-04-30 15:00:00","winner":"Fitzroy","timestr":null,"is_final":0,"id":26704,"hscore":36,"ateamid":19,"hbehinds":18,"hgoals":3,"year":1910,"hteam":"Essendon","unixtime":-1883160000,"localtime":"1910-04-30 14:00:00","ateam":"Fitzroy","hteamid":5,"updated":"2022-11-21 16:26:49","complete":100,"abehinds":10,"tz":"+11:00","agoals":9,"round":1},{"year":1910,"hteam":"Carlton","ateamid":4,"hbehinds":9,"hgoals":9,"localtime":"1910-04-30 14:00:00","unixtime":-1883160000,"hteamid":3,"complete":100,"updated":"2022-11-21 16:26:49","agoals":5,"tz":"+11:00","abehinds":5,"ateam":"Collingwood","round":1,"is_grand_final":0,"roundname":"Round 1","venue":"Princes Park","winnerteamid":3,"ascore":35,"timestr":null,"winner":"Carlton","date":"1910-04-30 15:00:00","id":26703,"hscore":63,"is_final":0},{"is_grand_final":0,"roundname":"Round 1","venue":"Lake Oval","winnerteamid":16,"ascore":32,"timestr":null,"date":"1910-04-30 15:00:00","winner":"Sydney","id":26706,"hscore":78,"is_final":0,"year":1910,"hteam":"Sydney","ateamid":14,"hbehinds":12,"hgoals":11,"localtime":"1910-04-30 14:00:00","unixtime":-1883160000,"updated":"2022-11-21 16:26:49","hteamid":16,"complete":100,"tz":"+11:00","abehinds":8,"agoals":4,"ateam":"Richmond","round":1},{"winnerteamid":7,"ascore":99,"is_grand_final":0,"roundname":"Round 1","venue":"M.C.G.","id":26705,"hscore":42,"is_final":0,"timestr":null,"winner":"Geelong","date":"1910-04-30 15:00:00","localtime":"1910-04-30 14:00:00","unixtime":-1883160000,"year":1910,"hteam":"Melbourne","ateamid":7,"hbehinds":6,"hgoals":6,"round":1,"complete":100,"hteamid":11,"updated":"2022-11-21 16:26:49","abehinds":21,"tz":"+11:00","agoals":13,"ateam":"Geelong"},{"date":"1910-04-30 15:00:00","winner":"University","timestr":null,"is_final":0,"id":26707,"hscore":30,"roundname":"Round 1","venue":"Junction Oval","is_grand_final":0,"winnerteamid":20,"ascore":52,"ateam":"University","hteamid":15,"updated":"2022-11-21 16:26:49","complete":100,"agoals":7,"tz":"+11:00","abehinds":10,"round":1,"ateamid":20,"hbehinds":12,"hgoals":3,"hteam":"St Kilda","year":1910,"unixtime":-1883160000,"localtime":"1910-04-30 14:00:00"},{"id":26752,"hscore":87,"is_final":0,"timestr":null,"date":"1910-05-14 15:00:00","winner":"Collingwood","winnerteamid":4,"ascore":46,"is_grand_final":0,"roundname":"Round 2","venue":"Victoria Park","round":2,"hteamid":4,"complete":100,"updated":"2022-11-21 16:26:49","abehinds":16,"tz":"+11:00","agoals":5,"ateam":"Sydney","localtime":"1910-05-14 14:00:00","unixtime":-1881950400,"year":1910,"hteam":"Collingwood","ateamid":16,"hgoals":13,"hbehinds":9},{"agoals":10,"tz":"+11:00","abehinds":15,"updated":"2022-11-21 16:26:49","hteamid":7,"complete":100,"ateam":"Carlton","round":2,"year":1910,"hteam":"Geelong","hgoals":6,"hbehinds":9,"ateamid":3,"localtime":"1910-05-14 14:00:00","unixtime":-1881950400,"timestr":null,"winner":"Carlton","date":"1910-05-14 15:00:00","hscore":45,"id":26751,"is_final":0,"is_grand_final":0,"venue":"Corio Oval","roundname":"Round 2","ascore":75,"winnerteamid":3},{"ateamid":11,"hgoals":16,"hbehinds":18,"year":1910,"hteam":"Richmond","unixtime":-1881950400,"localtime":"1910-05-14 14:00:00","ateam":"Melbourne","hteamid":14,"updated":"2022-11-21 16:26:49","complete":100,"agoals":5,"tz":"+11:00","abehinds":7,"round":2,"roundname":"Round 2","venue":"Punt Rd","is_grand_final":0,"winnerteamid":14,"ascore":37,"winner":"Richmond","date":"1910-05-14 15:00:00","timestr":null,"is_final":0,"id":26755,"hscore":114},{"localtime":"1910-05-14 14:00:00","unixtime":-1881950400,"year":1910,"hteam":"Fitzroy","hbehinds":15,"hgoals":14,"ateamid":15,"round":2,"agoals":4,"tz":"+11:00","abehinds":12,"hteamid":19,"complete":100,"updated":"2022-11-21 16:26:49","ateam":"St Kilda","ascore":36,"winnerteamid":19,"is_grand_final":0,"venue":"Brunswick St","roundname":"Round 2","hscore":99,"id":26754,"is_final":0,"timestr":null,"date":"1910-05-14 15:00:00","winner":"Fitzroy"},{"id":26753,"hscore":58,"is_final":0,"timestr":null,"date":"1910-05-14 15:00:00","winner":"Essendon","winnerteamid":5,"ascore":107,"is_grand_final":0,"roundname":"Round 2","venue":"East Melbourne","round":2,"hteamid":20,"updated":"2022-11-21 16:26:49","complete":100,"agoals":15,"tz":"+11:00","abehinds":17,"ateam":"Essendon","localtime":"1910-05-14 14:00:00","unixtime":-1881950400,"hteam":"University","year":1910,"ateamid":5,"hgoals":8,"hbehinds":10},{"winnerteamid":4,"ascore":18,"roundname":"Round 3","venue":"Victoria Park","is_grand_final":0,"is_final":0,"id":26747,"hscore":91,"winner":"Collingwood","date":"1910-05-21 15:00:00","timestr":null,"unixtime":-1881345600,"localtime":"1910-05-21 14:00:00","ateamid":15,"hgoals":13,"hbehinds":13,"year":1910,"hteam":"Collingwood","round":3,"ateam":"St Kilda","complete":100,"hteamid":4,"updated":"2022-11-21 16:26:49","abehinds":6,"tz":"+11:00","agoals":2},{"ascore":69,"winnerteamid":3,"venue":"M.C.G.","roundname":"Round 3","is_grand_final":0,"is_final":0,"hscore":36,"id":26746,"date":"1910-05-21 15:00:00","winner":"Carlton","timestr":null,"unixtime":-1881345600,"localtime":"1910-05-21 14:00:00","hgoals":5,"hbehinds":6,"ateamid":3,"hteam":"Melbourne","year":1910,"round":3,"ateam":"Carlton","abehinds":15,"tz":"+11:00","agoals":9,"hteamid":11,"updated":"2022-11-21 16:26:49","complete":100},{"timestr":null,"date":"1910-05-21 15:00:00","winner":"Essendon","id":26748,"hscore":67,"is_final":0,"is_grand_final":0,"roundname":"Round 3","venue":"Lake Oval","winnerteamid":5,"ascore":73,"complete":100,"hteamid":16,"updated":"2022-11-21 16:26:49","agoals":11,"tz":"+11:00","abehinds":7,"ateam":"Essendon","round":3,"hteam":"Sydney","year":1910,"ateamid":5,"hgoals":10,"hbehinds":7,"localtime":"1910-05-21 14:00:00","unixtime":-1881345600},{"date":"1910-05-21 15:00:00","winner":"Geelong","timestr":null,"is_final":0,"id":26749,"hscore":53,"roundname":"Round 3","venue":"Brunswick St","is_grand_final":0,"winnerteamid":7,"ascore":67,"ateam":"Geelong","hteamid":19,"complete":100,"updated":"2022-11-21 16:26:49","tz":"+11:00","abehinds":13,"agoals":9,"round":3,"ateamid":7,"hbehinds":11,"hgoals":7,"hteam":"Fitzroy","year":1910,"unixtime":-1881345600,"localtime":"1910-05-21 14:00:00"},{"winnerteamid":20,"ascore":52,"roundname":"Round 3","venue":"East Melbourne","is_grand_final":0,"is_final":0,"id":26750,"hscore":73,"winner":"University","date":"1910-05-21 15:00:00","timestr":null,"unixtime":-1881345600,"localtime":"1910-05-21 14:00:00","ateamid":14,"hgoals":10,"hbehinds":13,"year":1910,"hteam":"University","round":3,"ateam":"Richmond","hteamid":20,"complete":100,"updated":"2022-11-21 16:26:49","tz":"+11:00","agoals":7,"abehinds":10},{"id":26708,"hscore":49,"is_final":0,"timestr":null,"date":"1910-05-28 15:00:00","winner":"Carlton","winnerteamid":3,"ascore":32,"is_grand_final":0,"roundname":"Round 4","venue":"Princes Park","round":4,"hteamid":3,"updated":"2022-11-21 16:26:49","complete":100,"tz":"+11:00","agoals":4,"abehinds":8,"ateam":"Sydney","localtime":"1910-05-28 14:00:00","unixtime":-1880740800,"hteam":"Carlton","year":1910,"ateamid":16,"hgoals":6,"hbehinds":13},{"round":4,"ateam":"Melbourne","tz":"+11:00","abehinds":6,"agoals":8,"hteamid":15,"updated":"2022-11-21 16:26:49","complete":100,"unixtime":-1880740800,"localtime":"1910-05-28 14:00:00","hbehinds":9,"hgoals":7,"ateamid":11,"year":1910,"hteam":"St Kilda","is_final":0,"hscore":51,"id":26712,"winner":"Melbourne","date":"1910-05-28 15:00:00","timestr":null,"ascore":54,"winnerteamid":11,"venue":"Junction Oval","roundname":"Round 4","is_grand_final":0},{"venue":"Punt Rd","roundname":"Round 4","is_grand_final":0,"ascore":32,"winnerteamid":14,"date":"1910-05-28 15:00:00","winner":"Richmond","timestr":null,"is_final":0,"hscore":61,"id":26710,"hbehinds":19,"hgoals":7,"ateamid":19,"year":1910,"hteam":"Richmond","unixtime":-1880740800,"localtime":"1910-05-28 14:00:00","ateam":"Fitzroy","agoals":4,"tz":"+11:00","abehinds":8,"hteamid":14,"updated":"2022-11-21 16:26:49","complete":100,"round":4},{"winnerteamid":20,"ascore":58,"is_grand_final":0,"roundname":"Round 4","venue":"Corio Oval","id":26711,"hscore":45,"is_final":0,"timestr":null,"winner":"University","date":"1910-05-28 15:00:00","localtime":"1910-05-28 14:00:00","unixtime":-1880740800,"hteam":"Geelong","year":1910,"ateamid":20,"hbehinds":9,"hgoals":6,"round":4,"hteamid":7,"complete":100,"updated":"2022-11-21 16:26:49","abehinds":4,"tz":"+11:00","agoals":9,"ateam":"University"},{"ateam":"Collingwood","complete":100,"hteamid":5,"updated":"2022-11-21 16:26:49","abehinds":17,"tz":"+11:00","agoals":4,"round":4,"ateamid":4,"hgoals":6,"hbehinds":7,"hteam":"Essendon","year":1910,"unixtime":-1880740800,"localtime":"1910-05-28 14:00:00","date":"1910-05-28 15:00:00","winner":"Essendon","timestr":null,"is_final":0,"id":26709,"hscore":43,"roundname":"Round 4","venue":"East Melbourne","is_grand_final":0,"winnerteamid":5,"ascore":41},{"winnerteamid":4,"ascore":28,"is_grand_final":0,"roundname":"Round 5","venue":"Victoria Park","id":26782,"hscore":76,"is_final":0,"timestr":null,"winner":"Collingwood","date":"1910-06-04 15:00:00","localtime":"1910-06-04 14:00:00","unixtime":-1880136000,"year":1910,"hteam":"Collingwood","ateamid":11,"hbehinds":16,"hgoals":10,"round":5,"complete":100,"hteamid":4,"updated":"2022-11-21 16:26:49","abehinds":4,"tz":"+11:00","agoals":4,"ateam":"Melbourne"},{"round":5,"complete":100,"hteamid":5,"updated":"2022-11-21 16:26:49","tz":"+11:00","agoals":7,"abehinds":9,"ateam":"St Kilda","localtime":"1910-06-04 14:00:00","unixtime":-1880136000,"hteam":"Essendon","year":1910,"ateamid":15,"hgoals":8,"hbehinds":15,"id":26783,"hscore":63,"is_final":0,"timestr":null,"winner":"Essendon","date":"1910-06-04 15:00:00","winnerteamid":5,"ascore":51,"is_grand_final":0,"roundname":"Round 5","venue":"East Melbourne"},{"venue":"Corio Oval","roundname":"Round 5","is_grand_final":0,"ascore":29,"winnerteamid":7,"winner":"Geelong","date":"1910-06-04 15:00:00","timestr":null,"is_final":0,"hscore":46,"id":26784,"hbehinds":16,"hgoals":5,"ateamid":14,"year":1910,"hteam":"Geelong","unixtime":-1880136000,"localtime":"1910-06-04 14:00:00","ateam":"Richmond","tz":"+11:00","agoals":4,"abehinds":5,"hteamid":7,"complete":100,"updated":"2022-11-21 16:26:49","round":5},{"ascore":48,"winnerteamid":16,"is_grand_final":0,"venue":"Lake Oval","roundname":"Round 5","hscore":50,"id":26785,"is_final":0,"timestr":null,"winner":"Sydney","date":"1910-06-04 15:00:00","localtime":"1910-06-04 14:00:00","unixtime":-1880136000,"hteam":"Sydney","year":1910,"hbehinds":14,"hgoals":6,"ateamid":20,"round":5,"tz":"+11:00","abehinds":6,"agoals":7,"hteamid":16,"complete":100,"updated":"2022-11-21 16:26:49","ateam":"University"},{"date":"1910-06-04 15:00:00","winner":"Carlton","timestr":null,"is_final":0,"id":26781,"hscore":63,"roundname":"Round 5","venue":"Brunswick St","is_grand_final":0,"winnerteamid":3,"ascore":104,"ateam":"Carlton","updated":"2022-11-21 16:26:49","hteamid":19,"complete":100,"tz":"+11:00","agoals":14,"abehinds":20,"round":5,"ateamid":3,"hbehinds":9,"hgoals":9,"year":1910,"hteam":"Fitzroy","unixtime":-1880136000,"localtime":"1910-06-04 14:00:00"},{"ascore":42,"winnerteamid":7,"venue":"Corio Oval","roundname":"Round 6","is_grand_final":0,"is_final":0,"hscore":78,"id":26779,"date":"1910-06-06 15:00:00","winner":"Geelong","timestr":null,"unixtime":-1879963200,"localtime":"1910-06-06 14:00:00","hgoals":11,"hbehinds":12,"ateamid":16,"year":1910,"hteam":"Geelong","round":6,"ateam":"Sydney","tz":"+11:00","agoals":6,"abehinds":6,"hteamid":7,"updated":"2022-11-21 16:26:49","complete":100},{"ateam":"Carlton","abehinds":8,"tz":"+11:00","agoals":11,"updated":"2022-11-21 16:26:49","hteamid":20,"complete":100,"round":6,"hgoals":5,"hbehinds":5,"ateamid":3,"year":1910,"hteam":"University","unixtime":-1879963200,"localtime":"1910-06-06 14:00:00","date":"1910-06-06 15:00:00","winner":"Carlton","timestr":null,"is_final":0,"hscore":35,"id":26776,"venue":"East Melbourne","roundname":"Round 6","is_grand_final":0,"ascore":74,"winnerteamid":3},{"date":"1910-06-06 15:00:00","winner":"Collingwood","timestr":null,"is_final":0,"hscore":51,"id":26777,"venue":"Brunswick St","roundname":"Round 6","is_grand_final":0,"ascore":80,"winnerteamid":4,"ateam":"Collingwood","tz":"+11:00","abehinds":14,"agoals":11,"hteamid":19,"updated":"2022-11-21 16:26:49","complete":100,"round":6,"hgoals":7,"hbehinds":9,"ateamid":4,"hteam":"Fitzroy","year":1910,"unixtime":-1879963200,"localtime":"1910-06-06 14:00:00"},{"ateamid":5,"hgoals":10,"hbehinds":7,"hteam":"Melbourne","year":1910,"unixtime":-1879963200,"localtime":"1910-06-06 14:00:00","ateam":"Essendon","complete":100,"hteamid":11,"updated":"2022-11-21 16:26:49","agoals":16,"tz":"+11:00","abehinds":21,"round":6,"roundname":"Round 6","venue":"M.C.G.","is_grand_final":0,"winnerteamid":5,"ascore":117,"winner":"Essendon","date":"1910-06-06 15:00:00","timestr":null,"is_final":0,"id":26778,"hscore":67},{"round":6,"abehinds":14,"tz":"+11:00","agoals":8,"hteamid":15,"complete":100,"updated":"2022-11-21 16:26:49","ateam":"Richmond","localtime":"1910-06-06 14:00:00","unixtime":-1879963200,"hteam":"St Kilda","year":1910,"hbehinds":7,"hgoals":7,"ateamid":14,"hscore":49,"id":26780,"is_final":0,"timestr":null,"date":"1910-06-06 15:00:00","winner":"Richmond","ascore":62,"winnerteamid":14,"is_grand_final":0,"venue":"Junction Oval","roundname":"Round 6"},{"localtime":"1910-06-11 14:00:00","unixtime":-1879531200,"year":1910,"hteam":"Carlton","ateamid":5,"hbehinds":15,"hgoals":6,"round":7,"hteamid":3,"complete":100,"updated":"2022-11-21 16:26:49","abehinds":10,"tz":"+11:00","agoals":7,"ateam":"Essendon","winnerteamid":5,"ascore":52,"is_grand_final":0,"roundname":"Round 7","venue":"Princes Park","id":26736,"hscore":51,"is_final":0,"timestr":null,"winner":"Essendon","date":"1910-06-11 15:00:00"},{"ateam":"Collingwood","updated":"2022-11-21 16:26:49","hteamid":14,"complete":100,"tz":"+11:00","agoals":6,"abehinds":9,"round":7,"ateamid":4,"hbehinds":7,"hgoals":5,"year":1910,"hteam":"Richmond","unixtime":-1879531200,"localtime":"1910-06-11 14:00:00","winner":"Collingwood","date":"1910-06-11 15:00:00","timestr":null,"is_final":0,"id":26737,"hscore":37,"roundname":"Round 7","venue":"Punt Rd","is_grand_final":0,"winnerteamid":4,"ascore":45},{"localtime":"1910-06-11 14:00:00","unixtime":-1879531200,"hteam":"St Kilda","year":1910,"ateamid":7,"hbehinds":6,"hgoals":9,"round":7,"hteamid":15,"updated":"2022-11-21 16:26:49","complete":100,"tz":"+11:00","agoals":10,"abehinds":14,"ateam":"Geelong","winnerteamid":7,"ascore":74,"is_grand_final":0,"roundname":"Round 7","venue":"Junction Oval","id":26739,"hscore":60,"is_final":0,"timestr":null,"date":"1910-06-11 15:00:00","winner":"Geelong"},{"is_final":0,"hscore":81,"id":26740,"winner":"Sydney","date":"1910-06-11 15:00:00","timestr":null,"ascore":46,"winnerteamid":16,"venue":"Lake Oval","roundname":"Round 7","is_grand_final":0,"round":7,"ateam":"Melbourne","abehinds":10,"tz":"+11:00","agoals":6,"complete":100,"hteamid":16,"updated":"2022-11-21 16:26:49","unixtime":-1879531200,"localtime":"1910-06-11 14:00:00","hgoals":11,"hbehinds":15,"ateamid":11,"hteam":"Sydney","year":1910},{"round":7,"agoals":8,"tz":"+11:00","abehinds":8,"hteamid":20,"complete":100,"updated":"2022-11-21 16:26:49","ateam":"Fitzroy","localtime":"1910-06-11 14:00:00","unixtime":-1879531200,"hteam":"University","year":1910,"hgoals":13,"hbehinds":14,"ateamid":19,"hscore":92,"id":26738,"is_final":0,"timestr":null,"date":"1910-06-11 15:00:00","winner":"University","ascore":56,"winnerteamid":20,"is_grand_final":0,"venue":"East Melbourne","roundname":"Round 7"},{"venue":"Punt Rd","roundname":"Round 8","is_grand_final":0,"ascore":57,"winnerteamid":3,"winner":"Carlton","date":"1910-06-18 15:00:00","timestr":null,"is_final":0,"hscore":48,"id":26741,"hgoals":7,"hbehinds":6,"ateamid":3,"year":1910,"hteam":"Richmond","unixtime":-1878926400,"localtime":"1910-06-18 14:00:00","ateam":"Carlton","abehinds":15,"tz":"+11:00","agoals":7,"complete":100,"hteamid":14,"updated":"2022-11-21 16:26:49","round":8},{"ascore":49,"winnerteamid":16,"is_grand_final":0,"venue":"Junction Oval","roundname":"Round 8","hscore":29,"id":26745,"is_final":0,"timestr":null,"winner":"Sydney","date":"1910-06-18 15:00:00","localtime":"1910-06-18 14:00:00","unixtime":-1878926400,"year":1910,"hteam":"St Kilda","hbehinds":5,"hgoals":4,"ateamid":16,"round":8,"abehinds":13,"tz":"+11:00","agoals":6,"hteamid":15,"updated":"2022-11-21 16:26:49","complete":100,"ateam":"Sydney"},{"round":8,"ateam":"Fitzroy","hteamid":11,"complete":100,"updated":"2022-11-21 16:26:49","agoals":8,"tz":"+11:00","abehinds":18,"unixtime":-1878926400,"localtime":"1910-06-18 14:00:00","ateamid":19,"hgoals":6,"hbehinds":14,"hteam":"Melbourne","year":1910,"is_final":0,"id":26744,"hscore":50,"date":"1910-06-18 15:00:00","winner":"Fitzroy","timestr":null,"winnerteamid":19,"ascore":66,"roundname":"Round 8","venue":"M.C.G.","is_grand_final":0},{"roundname":"Round 8","venue":"East Melbourne","is_grand_final":0,"winnerteamid":5,"ascore":21,"winner":"Essendon","date":"1910-06-18 15:00:00","timestr":null,"is_final":0,"id":26743,"hscore":42,"ateamid":7,"hgoals":5,"hbehinds":12,"year":1910,"hteam":"Essendon","unixtime":-1878926400,"localtime":"1910-06-18 14:00:00","ateam":"Geelong","complete":100,"hteamid":5,"updated":"2022-11-21 16:26:49","tz":"+11:00","abehinds":9,"agoals":2,"round":8},{"winner":"Collingwood","date":"1910-06-18 15:00:00","timestr":null,"is_final":0,"id":26742,"hscore":46,"roundname":"Round 8","venue":"Victoria Park","is_grand_final":0,"winnerteamid":4,"ascore":42,"ateam":"University","hteamid":4,"complete":100,"updated":"2022-11-21 16:26:49","agoals":6,"tz":"+11:00","abehinds":6,"round":8,"ateamid":20,"hgoals":6,"hbehinds":10,"year":1910,"hteam":"Collingwood","unixtime":-1878926400,"localtime":"1910-06-18 14:00:00"},{"winner":"Carlton","date":"1910-06-25 15:00:00","timestr":null,"is_final":0,"hscore":64,"id":26786,"venue":"Princes Park","roundname":"Round 9","is_grand_final":0,"ascore":31,"winnerteamid":3,"ateam":"St Kilda","tz":"+11:00","agoals":4,"abehinds":7,"hteamid":3,"complete":100,"updated":"2022-11-21 16:26:49","round":9,"hgoals":9,"hbehinds":10,"ateamid":15,"year":1910,"hteam":"Carlton","unixtime":-1878321600,"localtime":"1910-06-25 14:00:00"},{"date":"1910-06-25 15:00:00","winner":"Geelong","timestr":null,"is_final":0,"id":26787,"hscore":69,"roundname":"Round 9","venue":"Corio Oval","is_grand_final":0,"winnerteamid":7,"ascore":47,"ateam":"Collingwood","hteamid":7,"updated":"2022-11-21 16:26:49","complete":100,"abehinds":11,"tz":"+11:00","agoals":6,"round":9,"ateamid":4,"hgoals":10,"hbehinds":9,"hteam":"Geelong","year":1910,"unixtime":-1878321600,"localtime":"1910-06-25 14:00:00"},{"round":9,"hteamid":14,"complete":100,"updated":"2022-11-21 16:26:49","abehinds":14,"tz":"+11:00","agoals":9,"ateam":"Essendon","localtime":"1910-06-25 14:00:00","unixtime":-1878321600,"hteam":"Richmond","year":1910,"ateamid":5,"hgoals":6,"hbehinds":10,"id":26788,"hscore":46,"is_final":0,"timestr":null,"date":"1910-06-25 15:00:00","winner":"Essendon","winnerteamid":5,"ascore":68,"is_grand_final":0,"roundname":"Round 9","venue":"Punt Rd"},{"is_grand_final":0,"roundname":"Round 9","venue":"Brunswick St","winnerteamid":16,"ascore":72,"timestr":null,"date":"1910-06-25 15:00:00","winner":"Sydney","id":26789,"hscore":55,"is_final":0,"hteam":"Fitzroy","year":1910,"ateamid":16,"hbehinds":13,"hgoals":7,"localtime":"1910-06-25 14:00:00","unixtime":-1878321600,"hteamid":19,"complete":100,"updated":"2022-11-21 16:26:49","agoals":11,"tz":"+11:00","abehinds":6,"ateam":"Sydney","round":9},{"ascore":35,"winnerteamid":20,"is_grand_final":0,"venue":"East Melbourne","roundname":"Round 9","hscore":49,"id":26790,"is_final":0,"timestr":null,"date":"1910-06-25 15:00:00","winner":"University","localtime":"1910-06-25 14:00:00","unixtime":-1878321600,"year":1910,"hteam":"University","hgoals":7,"hbehinds":7,"ateamid":11,"round":9,"abehinds":11,"tz":"+11:00","agoals":4,"complete":100,"hteamid":20,"updated":"2022-11-21 16:26:49","ateam":"Melbourne"},{"venue":"East Melbourne","roundname":"Round 10","is_grand_final":0,"ascore":45,"winnerteamid":20,"date":"1910-07-02 15:00:00","winner":"University","timestr":null,"is_final":0,"hscore":54,"id":26727,"hbehinds":12,"hgoals":7,"ateamid":15,"year":1910,"hteam":"University","unixtime":-1877716800,"localtime":"1910-07-02 14:00:00","ateam":"St Kilda","agoals":6,"tz":"+11:00","abehinds":9,"hteamid":20,"complete":100,"updated":"2022-11-21 16:26:49","round":10},{"venue":"Brunswick St","roundname":"Round 10","is_grand_final":0,"ascore":89,"winnerteamid":5,"winner":"Essendon","date":"1910-07-02 15:00:00","timestr":null,"is_final":0,"hscore":71,"id":26724,"hgoals":11,"hbehinds":5,"ateamid":5,"year":1910,"hteam":"Fitzroy","unixtime":-1877716800,"localtime":"1910-07-02 14:00:00","ateam":"Essendon","agoals":12,"tz":"+11:00","abehinds":17,"updated":"2022-11-21 16:26:49","hteamid":19,"complete":100,"round":10},{"is_final":0,"id":26726,"hscore":67,"winner":"Sydney","date":"1910-07-02 15:00:00","timestr":null,"winnerteamid":16,"ascore":71,"roundname":"Round 10","venue":"Punt Rd","is_grand_final":0,"round":10,"ateam":"Sydney","updated":"2022-11-21 16:26:49","hteamid":14,"complete":100,"tz":"+11:00","agoals":10,"abehinds":11,"unixtime":-1877716800,"localtime":"1910-07-02 14:00:00","ateamid":16,"hbehinds":7,"hgoals":10,"hteam":"Richmond","year":1910},{"round":10,"ateam":"Carlton","complete":100,"hteamid":4,"updated":"2022-11-21 16:26:49","agoals":6,"tz":"+11:00","abehinds":15,"unixtime":-1877716800,"localtime":"1910-07-02 14:00:00","ateamid":3,"hbehinds":10,"hgoals":2,"year":1910,"hteam":"Collingwood","is_final":0,"id":26723,"hscore":22,"date":"1910-07-02 15:00:00","winner":"Carlton","timestr":null,"winnerteamid":3,"ascore":51,"roundname":"Round 10","venue":"Victoria Park","is_grand_final":0},{"winnerteamid":7,"ascore":51,"is_grand_final":0,"roundname":"Round 10","venue":"Corio Oval","id":26725,"hscore":100,"is_final":0,"timestr":null,"winner":"Geelong","date":"1910-07-02 15:00:00","localtime":"1910-07-02 14:00:00","unixtime":-1877716800,"year":1910,"hteam":"Geelong","ateamid":11,"hbehinds":10,"hgoals":15,"round":10,"updated":"2022-11-21 16:26:49","hteamid":7,"complete":100,"abehinds":3,"tz":"+11:00","agoals":8,"ateam":"Melbourne"},{"winnerteamid":3,"ascore":33,"is_grand_final":0,"roundname":"Round 11","venue":"Princes Park","id":26771,"hscore":107,"is_final":0,"timestr":null,"winner":"Carlton","date":"1910-07-09 15:00:00","localtime":"1910-07-09 14:00:00","unixtime":-1877112000,"year":1910,"hteam":"Carlton","ateamid":7,"hbehinds":11,"hgoals":16,"round":11,"updated":"2022-11-21 16:26:49","hteamid":3,"complete":100,"abehinds":15,"tz":"+11:00","agoals":3,"ateam":"Geelong"},{"unixtime":-1877112000,"localtime":"1910-07-09 14:00:00","ateamid":20,"hgoals":8,"hbehinds":9,"year":1910,"hteam":"Essendon","round":11,"ateam":"University","hteamid":5,"complete":100,"updated":"2022-11-21 16:26:49","abehinds":9,"tz":"+11:00","agoals":11,"winnerteamid":20,"ascore":75,"roundname":"Round 11","venue":"East Melbourne","is_grand_final":0,"is_final":0,"id":26773,"hscore":57,"winner":"University","date":"1910-07-09 15:00:00","timestr":null},{"ateamid":14,"hgoals":4,"hbehinds":10,"hteam":"Melbourne","year":1910,"unixtime":-1877112000,"localtime":"1910-07-09 14:00:00","ateam":"Richmond","hteamid":11,"complete":100,"updated":"2022-11-21 16:26:49","tz":"+11:00","agoals":12,"abehinds":15,"round":11,"roundname":"Round 11","venue":"M.C.G.","is_grand_final":0,"winnerteamid":14,"ascore":87,"winner":"Richmond","date":"1910-07-09 15:00:00","timestr":null,"is_final":0,"id":26775,"hscore":34},{"ateamid":19,"hbehinds":10,"hgoals":4,"hteam":"St Kilda","year":1910,"unixtime":-1877112000,"localtime":"1910-07-09 14:00:00","ateam":"Fitzroy","updated":"2022-11-21 16:26:49","hteamid":15,"complete":100,"abehinds":14,"tz":"+11:00","agoals":8,"round":11,"roundname":"Round 11","venue":"Junction Oval","is_grand_final":0,"winnerteamid":19,"ascore":62,"winner":"Fitzroy","date":"1910-07-09 15:00:00","timestr":null,"is_final":0,"id":26774,"hscore":34},{"is_grand_final":0,"roundname":"Round 11","venue":"Lake Oval","winnerteamid":16,"ascore":33,"timestr":null,"winner":"Sydney","date":"1910-07-09 15:00:00","id":26772,"hscore":95,"is_final":0,"year":1910,"hteam":"Sydney","ateamid":4,"hbehinds":17,"hgoals":13,"localtime":"1910-07-09 14:00:00","unixtime":-1877112000,"hteamid":16,"complete":100,"updated":"2022-11-21 16:26:49","abehinds":9,"tz":"+11:00","agoals":4,"ateam":"Collingwood","round":11},{"unixtime":-1876507200,"localtime":"1910-07-16 14:00:00","ateamid":11,"hgoals":13,"hbehinds":22,"year":1910,"hteam":"Carlton","round":12,"ateam":"Melbourne","updated":"2022-11-21 16:26:49","hteamid":3,"complete":100,"tz":"+11:00","abehinds":11,"agoals":4,"winnerteamid":3,"ascore":35,"roundname":"Round 12","venue":"Princes Park","is_grand_final":0,"is_final":0,"id":26730,"hscore":100,"date":"1910-07-16 15:00:00","winner":"Carlton","timestr":null},{"is_grand_final":0,"roundname":"Round 12","venue":"East Melbourne","winnerteamid":5,"ascore":34,"timestr":null,"winner":"Essendon","date":"1910-07-16 15:00:00","id":26732,"hscore":45,"is_final":0,"year":1910,"hteam":"Essendon","ateamid":16,"hgoals":6,"hbehinds":9,"localtime":"1910-07-16 14:00:00","unixtime":-1876507200,"hteamid":5,"updated":"2022-11-21 16:26:49","complete":100,"tz":"+11:00","agoals":5,"abehinds":4,"ateam":"Sydney","round":12},{"timestr":null,"date":"1910-07-16 15:00:00","winner":"Geelong","id":26733,"hscore":72,"is_final":0,"is_grand_final":0,"roundname":"Round 12","venue":"Corio Oval","winnerteamid":7,"ascore":33,"complete":100,"hteamid":7,"updated":"2022-11-21 16:26:49","tz":"+11:00","agoals":4,"abehinds":9,"ateam":"Fitzroy","round":12,"hteam":"Geelong","year":1910,"ateamid":19,"hbehinds":6,"hgoals":11,"localtime":"1910-07-16 14:00:00","unixtime":-1876507200},{"year":1910,"hteam":"Richmond","hbehinds":11,"hgoals":5,"ateamid":20,"localtime":"1910-07-16 14:00:00","unixtime":-1876507200,"tz":"+11:00","abehinds":7,"agoals":10,"hteamid":14,"complete":100,"updated":"2022-11-21 16:26:49","ateam":"University","round":12,"is_grand_final":0,"venue":"Punt Rd","roundname":"Round 12","ascore":67,"winnerteamid":20,"timestr":null,"date":"1910-07-16 15:00:00","winner":"University","hscore":41,"id":26734,"is_final":0},{"date":"1910-07-16 15:00:00","winner":"Collingwood","timestr":null,"is_final":0,"id":26731,"hscore":44,"roundname":"Round 12","venue":"Junction Oval","is_grand_final":0,"winnerteamid":4,"ascore":54,"ateam":"Collingwood","updated":"2022-11-21 16:26:49","hteamid":15,"complete":100,"abehinds":12,"tz":"+11:00","agoals":7,"round":12,"ateamid":4,"hgoals":6,"hbehinds":8,"hteam":"St Kilda","year":1910,"unixtime":-1876507200,"localtime":"1910-07-16 14:00:00"},{"round":13,"ateam":"Essendon","hteamid":4,"complete":100,"updated":"2022-11-21 16:26:49","tz":"+11:00","agoals":2,"abehinds":9,"unixtime":-1875902400,"localtime":"1910-07-23 14:00:00","ateamid":5,"hgoals":5,"hbehinds":13,"year":1910,"hteam":"Collingwood","is_final":0,"id":26699,"hscore":43,"date":"1910-07-23 15:00:00","winner":"Collingwood","timestr":null,"winnerteamid":4,"ascore":21,"roundname":"Round 13","venue":"Victoria Park","is_grand_final":0},{"abehinds":8,"tz":"+11:00","agoals":5,"hteamid":20,"complete":100,"updated":"2022-11-21 16:26:49","ateam":"Geelong","round":13,"year":1910,"hteam":"University","hbehinds":13,"hgoals":8,"ateamid":7,"localtime":"1910-07-23 14:00:00","unixtime":-1875902400,"timestr":null,"winner":"University","date":"1910-07-23 15:00:00","hscore":61,"id":26701,"is_final":0,"is_grand_final":0,"venue":"East Melbourne","roundname":"Round 13","ascore":38,"winnerteamid":20},{"venue":"Brunswick St","roundname":"Round 13","is_grand_final":0,"ascore":35,"winnerteamid":14,"winner":"Richmond","date":"1910-07-23 15:00:00","timestr":null,"is_final":0,"hscore":25,"id":26700,"hgoals":3,"hbehinds":7,"ateamid":14,"hteam":"Fitzroy","year":1910,"unixtime":-1875902400,"localtime":"1910-07-23 14:00:00","ateam":"Richmond","tz":"+11:00","abehinds":5,"agoals":5,"hteamid":19,"updated":"2022-11-21 16:26:49","complete":100,"round":13},{"localtime":"1910-07-23 14:00:00","unixtime":-1875902400,"hteam":"Sydney","year":1910,"ateamid":3,"hbehinds":7,"hgoals":4,"round":13,"hteamid":16,"updated":"2022-11-21 16:26:49","complete":100,"tz":"+11:00","agoals":6,"abehinds":8,"ateam":"Carlton","winnerteamid":3,"ascore":44,"is_grand_final":0,"roundname":"Round 13","venue":"Lake Oval","id":26698,"hscore":31,"is_final":0,"timestr":null,"winner":"Carlton","date":"1910-07-23 15:00:00"},{"hgoals":6,"hbehinds":12,"ateamid":15,"hteam":"Melbourne","year":1910,"unixtime":-1875902400,"localtime":"1910-07-23 14:00:00","ateam":"St Kilda","tz":"+11:00","abehinds":11,"agoals":4,"updated":"2022-11-21 16:26:49","hteamid":11,"complete":100,"round":13,"venue":"M.C.G.","roundname":"Round 13","is_grand_final":0,"ascore":35,"winnerteamid":11,"winner":"Melbourne","date":"1910-07-23 15:00:00","timestr":null,"is_final":0,"hscore":48,"id":26702},{"round":14,"tz":"+11:00","abehinds":16,"agoals":4,"complete":100,"hteamid":3,"updated":"2022-11-21 16:26:49","ateam":"Fitzroy","localtime":"1910-07-30 14:00:00","unixtime":-1875297600,"year":1910,"hteam":"Carlton","hbehinds":13,"hgoals":5,"ateamid":19,"hscore":43,"id":26761,"is_final":0,"timestr":null,"winner":"Carlton","date":"1910-07-30 15:00:00","ascore":40,"winnerteamid":3,"is_grand_final":0,"venue":"Princes Park","roundname":"Round 14"},{"is_grand_final":0,"roundname":"Round 14","venue":"M.C.G.","winnerteamid":4,"ascore":66,"timestr":null,"winner":"Collingwood","date":"1910-07-30 15:00:00","id":26762,"hscore":48,"is_final":0,"year":1910,"hteam":"Melbourne","ateamid":4,"hgoals":7,"hbehinds":6,"localtime":"1910-07-30 14:00:00","unixtime":-1875297600,"updated":"2022-11-21 16:26:49","hteamid":11,"complete":100,"tz":"+11:00","agoals":9,"abehinds":12,"ateam":"Collingwood","round":14},{"winnerteamid":null,"ascore":42,"is_grand_final":0,"roundname":"Round 14","venue":"Punt Rd","id":26764,"hscore":42,"is_final":0,"timestr":null,"winner":null,"date":"1910-07-30 15:00:00","localtime":"1910-07-30 14:00:00","unixtime":-1875297600,"year":1910,"hteam":"Richmond","ateamid":7,"hgoals":5,"hbehinds":12,"round":14,"hteamid":14,"updated":"2022-11-21 16:26:49","complete":100,"agoals":6,"tz":"+11:00","abehinds":6,"ateam":"Geelong"},{"hteam":"St Kilda","year":1910,"hbehinds":8,"hgoals":5,"ateamid":5,"localtime":"1910-07-30 14:00:00","unixtime":-1875297600,"tz":"+11:00","abehinds":11,"agoals":11,"complete":100,"hteamid":15,"updated":"2022-11-21 16:26:49","ateam":"Essendon","round":14,"is_grand_final":0,"venue":"Junction Oval","roundname":"Round 14","ascore":77,"winnerteamid":5,"timestr":null,"winner":"Essendon","date":"1910-07-30 15:00:00","hscore":38,"id":26763,"is_final":0},{"ateam":"Sydney","hteamid":20,"updated":"2022-11-21 16:26:49","complete":100,"agoals":10,"tz":"+11:00","abehinds":7,"round":14,"ateamid":16,"hbehinds":6,"hgoals":3,"hteam":"University","year":1910,"unixtime":-1875297600,"localtime":"1910-07-30 14:00:00","date":"1910-07-30 15:00:00","winner":"Sydney","timestr":null,"is_final":0,"id":26765,"hscore":24,"roundname":"Round 14","venue":"East Melbourne","is_grand_final":0,"winnerteamid":16,"ascore":67},{"localtime":"1910-08-06 14:00:00","unixtime":-1874692800,"hteam":"Sydney","year":1910,"ateamid":7,"hgoals":11,"hbehinds":12,"round":15,"hteamid":16,"complete":100,"updated":"2022-11-21 16:26:49","agoals":3,"tz":"+11:00","abehinds":8,"ateam":"Geelong","winnerteamid":16,"ascore":26,"is_grand_final":0,"roundname":"Round 15","venue":"Lake Oval","id":26767,"hscore":78,"is_final":0,"timestr":null,"date":"1910-08-06 15:00:00","winner":"Sydney"},{"hteamid":4,"updated":"2022-11-21 16:26:49","complete":100,"tz":"+11:00","abehinds":6,"agoals":6,"ateam":"Fitzroy","round":15,"hteam":"Collingwood","year":1910,"ateamid":19,"hgoals":7,"hbehinds":12,"localtime":"1910-08-06 14:00:00","unixtime":-1874692800,"timestr":null,"winner":"Collingwood","date":"1910-08-06 15:00:00","id":26766,"hscore":54,"is_final":0,"is_grand_final":0,"roundname":"Round 15","venue":"Victoria Park","winnerteamid":4,"ascore":42},{"ateam":"St Kilda","abehinds":10,"tz":"+11:00","agoals":1,"hteamid":14,"complete":100,"updated":"2022-11-21 16:26:49","round":15,"hbehinds":6,"hgoals":8,"ateamid":15,"hteam":"Richmond","year":1910,"unixtime":-1874692800,"localtime":"1910-08-06 14:00:00","winner":"Richmond","date":"1910-08-06 15:00:00","timestr":null,"is_final":0,"hscore":54,"id":26768,"venue":"Punt Rd","roundname":"Round 15","is_grand_final":0,"ascore":16,"winnerteamid":14},{"winner":"Carlton","date":"1910-08-13 15:00:00","timestr":null,"is_final":0,"id":26769,"hscore":78,"roundname":"Round 15","venue":"Princes Park","is_grand_final":0,"winnerteamid":3,"ascore":50,"ateam":"University","complete":100,"hteamid":3,"updated":"2022-11-21 16:26:49","tz":"+11:00","abehinds":14,"agoals":6,"round":15,"ateamid":20,"hbehinds":12,"hgoals":11,"year":1910,"hteam":"Carlton","unixtime":-1874088000,"localtime":"1910-08-13 14:00:00"},{"unixtime":-1874088000,"localtime":"1910-08-13 14:00:00","hbehinds":18,"hgoals":4,"ateamid":11,"year":1910,"hteam":"Essendon","round":15,"ateam":"Melbourne","tz":"+11:00","agoals":7,"abehinds":12,"updated":"2022-11-21 16:26:49","hteamid":5,"complete":100,"ascore":54,"winnerteamid":11,"venue":"East Melbourne","roundname":"Round 15","is_grand_final":0,"is_final":0,"hscore":42,"id":26770,"winner":"Melbourne","date":"1910-08-13 15:00:00","timestr":null},{"ateam":"Richmond","hteamid":4,"updated":"2022-11-21 16:08:26","complete":100,"agoals":5,"tz":"+11:00","abehinds":4,"round":16,"ateamid":14,"hbehinds":13,"hgoals":8,"year":1910,"hteam":"Collingwood","unixtime":-1873483200,"localtime":"1910-08-20 14:00:00","date":"1910-08-20 15:00:00","winner":"Collingwood","timestr":null,"is_final":0,"id":25513,"hscore":61,"roundname":"Round 16","venue":"Victoria Park","is_grand_final":0,"winnerteamid":4,"ascore":34},{"round":16,"abehinds":10,"tz":"+11:00","agoals":7,"hteamid":5,"complete":100,"updated":"2022-11-21 16:08:26","ateam":"Carlton","localtime":"1910-08-20 14:00:00","unixtime":-1873483200,"year":1910,"hteam":"Essendon","hgoals":8,"hbehinds":12,"ateamid":3,"hscore":60,"id":25512,"is_final":0,"timestr":null,"date":"1910-08-20 15:00:00","winner":"Essendon","ascore":52,"winnerteamid":5,"is_grand_final":0,"venue":"East Melbourne","roundname":"Round 16"},{"winnerteamid":7,"ascore":24,"roundname":"Round 16","venue":"Corio Oval","is_grand_final":0,"is_final":0,"id":26759,"hscore":53,"date":"1910-08-20 15:00:00","winner":"Geelong","timestr":null,"unixtime":-1873483200,"localtime":"1910-08-20 14:00:00","ateamid":15,"hgoals":7,"hbehinds":11,"hteam":"Geelong","year":1910,"round":16,"ateam":"St Kilda","hteamid":7,"updated":"2022-11-21 16:26:49","complete":100,"tz":"+11:00","abehinds":6,"agoals":3},{"timestr":null,"date":"1910-08-20 15:00:00","winner":"Sydney","hscore":54,"id":26760,"is_final":0,"is_grand_final":0,"venue":"M.C.G.","roundname":"Round 16","ascore":58,"winnerteamid":16,"tz":"+11:00","abehinds":10,"agoals":8,"updated":"2022-11-21 16:26:49","hteamid":11,"complete":100,"ateam":"Sydney","round":16,"hteam":"Melbourne","year":1910,"hgoals":8,"hbehinds":6,"ateamid":16,"localtime":"1910-08-20 14:00:00","unixtime":-1873483200},{"venue":"Brunswick St","roundname":"Round 16","is_grand_final":0,"ascore":48,"winnerteamid":20,"date":"1910-08-20 15:00:00","winner":"University","timestr":null,"is_final":0,"hscore":23,"id":26758,"hbehinds":5,"hgoals":3,"ateamid":20,"hteam":"Fitzroy","year":1910,"unixtime":-1873483200,"localtime":"1910-08-20 14:00:00","ateam":"University","tz":"+11:00","abehinds":6,"agoals":7,"hteamid":19,"updated":"2022-11-21 16:26:49","complete":100,"round":16},{"localtime":"1910-08-27 14:00:00","unixtime":-1872878400,"year":1910,"hteam":"Fitzroy","hbehinds":16,"hgoals":12,"ateamid":11,"round":17,"tz":"+11:00","abehinds":11,"agoals":2,"hteamid":19,"updated":"2022-11-21 16:26:49","complete":100,"ateam":"Melbourne","ascore":23,"winnerteamid":19,"is_grand_final":0,"venue":"Brunswick St","roundname":"Round 17","hscore":88,"id":26721,"is_final":0,"timestr":null,"winner":"Fitzroy","date":"1910-08-27 15:00:00"},{"is_grand_final":0,"roundname":"Round 17","venue":"East Melbourne","winnerteamid":4,"ascore":75,"timestr":null,"date":"1910-08-27 15:00:00","winner":"Collingwood","id":26719,"hscore":59,"is_final":0,"year":1910,"hteam":"University","ateamid":4,"hgoals":9,"hbehinds":5,"localtime":"1910-08-27 14:00:00","unixtime":-1872878400,"hteamid":20,"complete":100,"updated":"2022-11-21 16:26:49","abehinds":15,"tz":"+11:00","agoals":10,"ateam":"Collingwood","round":17},{"ateam":"St Kilda","agoals":10,"tz":"+11:00","abehinds":5,"complete":100,"hteamid":16,"updated":"2022-11-21 16:26:49","round":17,"hgoals":11,"hbehinds":11,"ateamid":15,"year":1910,"hteam":"Sydney","unixtime":-1872878400,"localtime":"1910-08-27 14:00:00","date":"1910-08-27 15:00:00","winner":"Sydney","timestr":null,"is_final":0,"hscore":77,"id":26722,"venue":"Lake Oval","roundname":"Round 17","is_grand_final":0,"ascore":65,"winnerteamid":16},{"winnerteamid":7,"ascore":71,"is_grand_final":0,"roundname":"Round 17","venue":"Corio Oval","id":26720,"hscore":79,"is_final":0,"timestr":null,"winner":"Geelong","date":"1910-08-27 15:00:00","localtime":"1910-08-27 14:00:00","unixtime":-1872878400,"hteam":"Geelong","year":1910,"ateamid":5,"hbehinds":19,"hgoals":10,"round":17,"updated":"2022-11-21 16:26:49","hteamid":7,"complete":100,"abehinds":11,"tz":"+11:00","agoals":10,"ateam":"Essendon"},{"round":17,"hteamid":3,"complete":100,"updated":"2022-11-21 16:26:49","tz":"+11:00","agoals":6,"abehinds":9,"ateam":"Richmond","localtime":"1910-08-27 14:00:00","unixtime":-1872878400,"hteam":"Carlton","year":1910,"ateamid":14,"hbehinds":8,"hgoals":9,"id":26718,"hscore":62,"is_final":0,"timestr":null,"date":"1910-08-27 15:00:00","winner":"Carlton","winnerteamid":3,"ascore":45,"is_grand_final":0,"roundname":"Round 17","venue":"Princes Park"},{"hteam":"Collingwood","year":1910,"hbehinds":13,"hgoals":4,"ateamid":7,"localtime":"1910-09-03 14:00:00","unixtime":-1872273600,"abehinds":9,"tz":"+11:00","agoals":2,"updated":"2022-11-21 16:26:49","hteamid":4,"complete":100,"ateam":"Geelong","round":18,"is_grand_final":0,"venue":"Victoria Park","roundname":"Round 18","ascore":21,"winnerteamid":4,"timestr":null,"winner":"Collingwood","date":"1910-09-03 15:00:00","hscore":37,"id":26714,"is_final":0},{"is_final":0,"id":26715,"hscore":50,"date":"1910-09-03 15:00:00","winner":"Richmond","timestr":null,"winnerteamid":14,"ascore":51,"roundname":"Round 18","venue":"East Melbourne","is_grand_final":0,"round":18,"ateam":"Richmond","updated":"2022-11-21 16:26:49","hteamid":5,"complete":100,"tz":"+11:00","agoals":7,"abehinds":9,"unixtime":-1872273600,"localtime":"1910-09-03 14:00:00","ateamid":14,"hgoals":6,"hbehinds":14,"year":1910,"hteam":"Essendon"},{"venue":"M.C.G.","roundname":"Round 18","is_grand_final":0,"ascore":49,"winnerteamid":11,"winner":"Melbourne","date":"1910-09-03 15:00:00","timestr":null,"is_final":0,"hscore":60,"id":26717,"hgoals":9,"hbehinds":6,"ateamid":20,"hteam":"Melbourne","year":1910,"unixtime":-1872273600,"localtime":"1910-09-03 14:00:00","ateam":"University","tz":"+11:00","agoals":7,"abehinds":7,"updated":"2022-11-21 16:26:49","hteamid":11,"complete":100,"round":18},{"ateamid":3,"hgoals":5,"hbehinds":6,"hteam":"St Kilda","year":1910,"unixtime":-1872273600,"localtime":"1910-09-03 14:00:00","ateam":"Carlton","complete":100,"hteamid":15,"updated":"2022-11-21 16:26:49","tz":"+11:00","abehinds":12,"agoals":2,"round":18,"roundname":"Round 18","venue":"Junction Oval","is_grand_final":0,"winnerteamid":15,"ascore":24,"date":"1910-09-03 15:00:00","winner":"St Kilda","timestr":null,"is_final":0,"id":26713,"hscore":36},{"winner":"Sydney","date":"1910-09-03 15:00:00","timestr":null,"is_final":0,"id":26716,"hscore":52,"roundname":"Round 18","venue":"Lake Oval","is_grand_final":0,"winnerteamid":16,"ascore":29,"ateam":"Fitzroy","complete":100,"hteamid":16,"updated":"2022-11-21 16:26:49","abehinds":5,"tz":"+11:00","agoals":4,"round":18,"ateamid":19,"hgoals":7,"hbehinds":10,"year":1910,"hteam":"Sydney","unixtime":-1872273600,"localtime":"1910-09-03 14:00:00"},{"ateamid":5,"hbehinds":11,"hgoals":14,"year":1910,"hteam":"Collingwood","unixtime":-1871670600,"localtime":"1910-09-10 13:30:00","ateam":"Essendon","hteamid":4,"updated":"2022-11-21 16:26:49","complete":100,"abehinds":7,"tz":"+11:00","agoals":5,"round":19,"roundname":"Finals Week 1","venue":"M.C.G.","is_grand_final":0,"winnerteamid":4,"ascore":37,"winner":"Collingwood","date":"1910-09-10 14:30:00","timestr":null,"is_final":1,"id":26735,"hscore":95},{"is_final":1,"hscore":65,"id":26729,"winner":"Sydney","date":"1910-09-17 14:30:00","timestr":null,"ascore":53,"winnerteamid":16,"venue":"M.C.G.","roundname":"Semi-Finals","is_grand_final":0,"round":20,"ateam":"Carlton","tz":"+11:00","agoals":6,"abehinds":17,"hteamid":16,"complete":100,"updated":"2022-11-21 16:26:49","unixtime":-1871065800,"localtime":"1910-09-17 13:30:00","hbehinds":5,"hgoals":10,"ateamid":3,"year":1910,"hteam":"Sydney"},{"ascore":44,"winnerteamid":4,"venue":"M.C.G.","roundname":"Preliminary Finals","is_grand_final":0,"is_final":1,"hscore":55,"id":26697,"winner":"Collingwood","date":"1910-09-24 14:30:00","timestr":null,"unixtime":-1870461000,"localtime":"1910-09-24 13:30:00","hbehinds":7,"hgoals":8,"ateamid":16,"year":1910,"hteam":"Collingwood","round":21,"ateam":"Sydney","agoals":6,"tz":"+11:00","abehinds":8,"hteamid":4,"complete":100,"updated":"2022-11-21 16:26:49"},{"date":"1910-10-01 14:50:00","winner":"Collingwood","timestr":null,"is_final":1,"hscore":61,"id":26728,"venue":"M.C.G.","roundname":"Grand Final","is_grand_final":1,"ascore":47,"winnerteamid":4,"ateam":"Carlton","agoals":6,"tz":"+11:00","abehinds":11,"complete":100,"hteamid":4,"updated":"2022-11-21 16:26:49","round":22,"hbehinds":7,"hgoals":9,"ateamid":3,"year":1910,"hteam":"Collingwood","unixtime":-1869855000,"localtime":"1910-10-01 13:50:00"}]}